odoo/addons/energiabonita/__init__.py
odoo/addons/energiabonita/__manifest__.py
odoo/addons/energiabonita/controllers/__init__.py
odoo/addons/energiabonita/controllers/website_subscription.py
odoo/addons/energiabonita/i18n/es.po
odoo/addons/energiabonita/models/__init__.py
odoo/addons/energiabonita/models/company.py
odoo/addons/energiabonita/models/subscription_request.py
odoo/addons/energiabonita/views/become_company_cooperator_view.xml
odoo/addons/energiabonita/views/become_cooperator_view.xml
odoo/addons/energiabonita/views/res_company_view.xml
odoo/addons/energiabonita/views/subscription_request_view.xml
odoo12_addon_energiabonita-12.0.0.0.1.dist-info/METADATA
odoo12_addon_energiabonita-12.0.0.0.1.dist-info/WHEEL
odoo12_addon_energiabonita-12.0.0.0.1.dist-info/top_level.txt
odoo12_addon_energiabonita-12.0.0.0.1.dist-info/RECORD
